AUTHORS.txt
CHANGELOG.md
LICENSE.txt
MANIFEST.in
PyPI-README.rst
README.rst
setup.cfg
setup.json
setup.py
aiida_siesta/__init__.py
aiida_siesta.egg-info/PKG-INFO
aiida_siesta.egg-info/SOURCES.txt
aiida_siesta.egg-info/dependency_links.txt
aiida_siesta.egg-info/entry_points.txt
aiida_siesta.egg-info/requires.txt
aiida_siesta.egg-info/top_level.txt
aiida_siesta/calculations/__init__.py
aiida_siesta/calculations/siesta.py
aiida_siesta/calculations/stm.py
aiida_siesta/calculations/tkdict.py
aiida_siesta/commands/__init__.py
aiida_siesta/commands/data_psf.py
aiida_siesta/commands/data_psml.py
aiida_siesta/data/__init__.py
aiida_siesta/data/atomic_orbitals.py
aiida_siesta/data/common.py
aiida_siesta/data/ion.py
aiida_siesta/data/psf.py
aiida_siesta/data/psml.py
aiida_siesta/examples/00_README
aiida_siesta/examples/__init__.py
aiida_siesta/examples/fixtures/O2_ICSD_173933.cif
aiida_siesta/examples/fixtures/Si.ion.xml
aiida_siesta/examples/fixtures/__init__.py
aiida_siesta/examples/fixtures/lua_scripts/neb.lua
aiida_siesta/examples/fixtures/lua_scripts/relax_geometry_lbfgs.lua
aiida_siesta/examples/fixtures/neb_data/image-0.xyz
aiida_siesta/examples/fixtures/neb_data/image-1.xyz
aiida_siesta/examples/fixtures/neb_data/image-2.xyz
aiida_siesta/examples/fixtures/neb_data/image-3.xyz
aiida_siesta/examples/fixtures/neb_data/image-4.xyz
aiida_siesta/examples/fixtures/neb_data/image-5.xyz
aiida_siesta/examples/fixtures/neb_data/image-6.xyz
aiida_siesta/examples/fixtures/sample_psf/C.psf
aiida_siesta/examples/fixtures/sample_psf/Cr.psf
aiida_siesta/examples/fixtures/sample_psf/Fe.psf
aiida_siesta/examples/fixtures/sample_psf/Ge.psf
aiida_siesta/examples/fixtures/sample_psf/H.psf
aiida_siesta/examples/fixtures/sample_psf/O.psf
aiida_siesta/examples/fixtures/sample_psf/Si.psf
aiida_siesta/examples/fixtures/sample_psml/Ba.sc-ionic-siesta-vnl.psml
aiida_siesta/examples/fixtures/sample_psml/C.psml
aiida_siesta/examples/fixtures/sample_psml/H.psml
aiida_siesta/examples/fixtures/sample_psml/Hg.psml
aiida_siesta/examples/fixtures/sample_psml/O.psml
aiida_siesta/examples/fixtures/sample_psml/Si.psml
aiida_siesta/examples/fixtures/sample_psml/fe.spin.psml
aiida_siesta/examples/plugins/00_README
