Metadata-Version: 2.1
Name: aiida-siesta
Version: 1.4.0
Summary: A plugin for Siesta's basic functionality within the AiiDA framework.
Home-page: https://github.com/siesta-project/aiida_siesta_plugin
Author: Alberto Garcia, Victor M. Garcia-Suarez, Emanuele Bosoni, Vladimir Dikan, Pol Febrer
Author-email: albertog@icmab.es
License: MIT License
Keywords: aiida,siesta,dft
Platform: UNKNOWN
Classifier: License :: OSI Approved :: MIT License
Classifier: Programming Language :: Python :: 3.7
Classifier: Programming Language :: Python :: 3.8
Classifier: Programming Language :: Python :: 3.9
Classifier: Development Status :: 5 - Production/Stable
Classifier: Framework :: AiiDA
Provides-Extra: dev
Provides-Extra: docs
License-File: LICENSE.txt
License-File: AUTHORS.txt
